calibplot/__init__.py
calibplot/calfetcher.py
ligo_calibplot-0.0.4.dist-info/METADATA
ligo_calibplot-0.0.4.dist-info/WHEEL
ligo_calibplot-0.0.4.dist-info/top_level.txt
ligo_calibplot-0.0.4.dist-info/RECORD
