Metadata-Version: 2.1
Name: ligo-calibplot
Version: 0.0.4
Summary: Tool for querying and plotting LIGO calibration monitoring data from influxDB.
Author-email: Matthew Carney <matthew.carney@ligo.org>
Project-URL: Homepage, https://git.ligo.org/matthew.carney/ligo-calibplot
Project-URL: Bug Tracker, https://git.ligo.org/matthew.carney/ligo-calibplot/-/issues
Classifier: Programming Language :: Python :: 3
Classifier: License :: OSI Approved :: MIT License
Classifier: Operating System :: OS Independent
Requires-Python: >=3.7
Requires-Dist: pandas
Requires-Dist: matplotlib
Requires-Dist: ligo-scald
Requires-Dist: configparser
